README.rst
setup.cfg
setup.py
plotly/__init__.py
plotly/colors.py
plotly/exceptions.py
plotly/files.py
plotly/graph_reference.py
plotly/session.py
plotly/tools.py
plotly/utils.py
plotly/version.py
plotly/graph_objs/__init__.py
plotly/graph_objs/graph_objs.py
plotly/graph_objs/graph_objs_tools.py
plotly/graph_reference/default-schema.json
plotly/grid_objs/__init__.py
plotly/grid_objs/grid_objs.py
plotly/matplotlylib/__init__.py
plotly/matplotlylib/mpltools.py
plotly/matplotlylib/renderer.py
plotly/matplotlylib/mplexporter/__init__.py
plotly/matplotlylib/mplexporter/_py3k_compat.py
plotly/matplotlylib/mplexporter/exporter.py
plotly/matplotlylib/mplexporter/tools.py
plotly/matplotlylib/mplexporter/utils.py
plotly/matplotlylib/mplexporter/renderers/__init__.py
plotly/matplotlylib/mplexporter/renderers/base.py
plotly/matplotlylib/mplexporter/renderers/fake_renderer.py
plotly/matplotlylib/mplexporter/renderers/vega_renderer.py
plotly/matplotlylib/mplexporter/renderers/vincent_renderer.py
plotly/offline/__init__.py
plotly/offline/offline.py
plotly/offline/plotly.min.js
plotly/plotly/__init__.py
plotly/plotly/plotly.py
plotly/plotly/chunked_requests/__init__.py
plotly/plotly/chunked_requests/chunked_request.py
plotly/widgets/__init__.py
plotly/widgets/graphWidget.js
plotly/widgets/graph_widget.py
plotly_modified.egg-info/PKG-INFO
plotly_modified.egg-info/SOURCES.txt
plotly_modified.egg-info/dependency_links.txt
plotly_modified.egg-info/not-zip-safe
plotly_modified.egg-info/requires.txt
plotly_modified.egg-info/top_level.txt