Metadata-Version: 1.1
Name: plotly-modified
Version: 0.1.1
Summary: Python plotting library for collaborative, interactive, publication-quality graphs.
Home-page: https://github.com/tonykzeng/plotly.py
Author: Tony Z
Author-email: tonykzeng@gmail.com
License: MIT
Download-URL: https://github.com/tonykzeng/plotly.py/tarball/0.1.1
Platform: UNKNOWN
Classifier: Development Status :: 4 - Beta
Classifier: Programming Language :: Python :: 2
Classifier: Programming Language :: Python :: 2.7
Classifier: Programming Language :: Python :: 3
Classifier: Programming Language :: Python :: 3.2
Classifier: Programming Language :: Python :: 3.3
Classifier: Programming Language :: Python :: 3.4
Classifier: Topic :: Scientific/Engineering :: Visualization
